pre_commit_fluent_hook/__init__.py
pre_commit_fluent_hook/check_fluent.py
pre_commit_fluent_hook-0.0.1.dist-info/licenses/LICENSE
pre_commit_fluent_hook-0.0.1.dist-info/METADATA
pre_commit_fluent_hook-0.0.1.dist-info/WHEEL
pre_commit_fluent_hook-0.0.1.dist-info/entry_points.txt
pre_commit_fluent_hook-0.0.1.dist-info/top_level.txt
pre_commit_fluent_hook-0.0.1.dist-info/RECORD
