Metadata-Version: 2.4
Name: pre-commit-fluent-hook
Version: 0.0.1
Summary: A pre-commit hook for validating Fluent (FTL) files
Author: uutils Contributors
License: MIT
Project-URL: Homepage, https://github.com/uutils/pre-commit-fluent-hook
Classifier: Programming Language :: Python :: 3
Classifier: Programming Language :: Python :: 3 :: Only
Classifier: Programming Language :: Python :: Implementation :: CPython
Classifier: Programming Language :: Python :: Implementation :: PyPy
Classifier: License :: OSI Approved :: MIT License
Requires-Python: >=3.9
License-File: LICENSE
Dynamic: license-file
